cognite/extractorutils/cogex/__init__.py
cognite/extractorutils/cogex/__main__.py
cognite/extractorutils/cogex/_common.py
cognite/extractorutils/cogex/build.py
cognite/extractorutils/cogex/docker.py
cognite/extractorutils/cogex/initialize.py
cognite/extractorutils/cogex/io.py
cognite_extractor_manager-2.0.0.dist-info/METADATA
cognite_extractor_manager-2.0.0.dist-info/WHEEL
cognite_extractor_manager-2.0.0.dist-info/entry_points.txt
cognite_extractor_manager-2.0.0.dist-info/licenses/LICENSE
cognite_extractor_manager-2.0.0.dist-info/RECORD
