Metadata-Version: 2.4
Name: cognite-extractor-manager
Version: 2.0.0
Summary: A project manager for Python based extractors
Author-email: Mathias Lohne <mathias.lohne@cognite.com>
License: Apache-2.0
License-File: LICENSE
Requires-Python: >=3.10
Requires-Dist: pyhumps>=3.8.0
Requires-Dist: requests>=2.32.3
Requires-Dist: termcolor>=2.5.0
Requires-Dist: toml>=0.10.2
